LICENSE
MANIFEST.in
README.rst
build-requirements.pip
setup.py
test_settings.py
pammy/__init__.py
pammy/admin.py
pammy/app_settings.py
pammy/autoconfig.py
pammy/fields.py
pammy/forms.py
pammy/models.py
pammy/urls.py
pammy/utils.py
pammy/version.py
pammy.egg-info/PKG-INFO
pammy.egg-info/SOURCES.txt
pammy.egg-info/dependency_links.txt
pammy.egg-info/requires.txt
pammy.egg-info/top_level.txt
pammy/api/__init__.py
pammy/api/v1/__init__.py
pammy/api/v1/resources/__init__.py
pammy/views/__init__.py
pammy/views/ui.py